django/__init__.py
django/__main__.py
django/shortcuts.py
django/apps/__init__.py
django/apps/config.py
django/apps/registry.py
django/conf/__init__.py
django/conf/global_settings.py
django/conf/urls/__init__.py
django/conf/urls/static.py
django/contrib/__init__.py
django/contrib/messages/__init__.py
django/contrib/messages/api.py
django/contrib/messages/apps.py
django/contrib/messages/constants.py
django/contrib/messages/context_processors.py
django/contrib/messages/middleware.py
django/contrib/messages/utils.py
django/contrib/messages/views.py
django/contrib/messages/storage/__init__.py
django/contrib/messages/storage/base.py
django/contrib/messages/storage/cookie.py
django/contrib/messages/storage/fallback.py
django/contrib/messages/storage/session.py
django/contrib/redirects/__init__.py
django/contrib/redirects/admin.py
django/contrib/redirects/apps.py
django/contrib/redirects/middleware.py
django/contrib/redirects/models.py
django/contrib/redirects/migrations/0001_initial.py
django/contrib/redirects/migrations/0002_alter_redirect_new_path_help_text.py
django/contrib/redirects/migrations/__init__.py
django/contrib/sessions/__init__.py
django/contrib/sessions/apps.py
django/contrib/sessions/base_session.py
django/contrib/sessions/exceptions.py
django/contrib/sessions/middleware.py
django/contrib/sessions/models.py
django/contrib/sessions/serializers.py
django/contrib/sessions/backends/__init__.py
django/contrib/sessions/backends/base.py
django/contrib/sessions/backends/cache.py
django/contrib/sessions/backends/cached_db.py
django/contrib/sessions/backends/db.py
django/contrib/sessions/backends/file.py
django/contrib/sessions/backends/signed_cookies.py
django/contrib/sessions/management/__init__.py
django/contrib/sessions/management/commands/__init__.py
django/contrib/sessions/management/commands/clearsessions.py
django/contrib/sessions/migrations/0001_initial.py
django/contrib/sessions/migrations/__init__.py
django/contrib/staticfiles/__init__.py
django_lightweight-0.2.dist-info/METADATA
django_lightweight-0.2.dist-info/WHEEL
django_lightweight-0.2.dist-info/entry_points.txt
django_lightweight-0.2.dist-info/top_level.txt
django_lightweight-0.2.dist-info/RECORD
